orderings/__init__.py
orderings/core.py
orderings/py.typed
orderings/typing.py
orderings-1.5.0.dist-info/LICENSE
orderings-1.5.0.dist-info/METADATA
orderings-1.5.0.dist-info/WHEEL
orderings-1.5.0.dist-info/RECORD
