Metadata-Version: 2.1
Name: orderings
Version: 1.5.0
Summary: Ordering enumeration and protocols.
Home-page: https://github.com/nekitdev/orderings
License: MIT
Keywords: python,ordering
Author: nekitdev
Requires-Python: >=3.8
Classifier: Development Status :: 5 - Production/Stable
Classifier: Intended Audience :: Developers
Classifier: License :: OSI Approved :: MIT License
Classifier: Operating System :: OS Independent
Classifier: Programming Language :: Python :: 3
Classifier: Programming Language :: Python :: 3.8
Classifier: Programming Language :: Python :: 3.9
Classifier: Programming Language :: Python :: 3.10
Classifier: Programming Language :: Python :: 3.11
Classifier: Programming Language :: Python :: 3.12
Classifier: Topic :: Utilities
Classifier: Typing :: Typed
Requires-Dist: typing-aliases (>=1.10.1)
Requires-Dist: typing-extensions (>=4.12.1)
Project-URL: Chat, https://nekit.dev/chat
Project-URL: Documentation, https://nekitdev.github.io/orderings
Project-URL: Funding, https://nekit.dev/funding
Project-URL: Issues, https://github.com/nekitdev/orderings/issues
Project-URL: Repository, https://github.com/nekitdev/orderings
